nemea_pytrap.libs/libcrypto-401bea5d.so.1.1.1k
nemea_pytrap.libs/libssl-52849bc7.so.1.1.1k
nemea_pytrap.libs/libtrap-473ac5f9.so.1.5.0
nemea_pytrap-0.17.0.dist-info/top_level.txt
nemea_pytrap-0.17.0.dist-info/METADATA
nemea_pytrap-0.17.0.dist-info/RECORD
nemea_pytrap-0.17.0.dist-info/WHEEL
pytrap/pytrap.cpython-39-x86_64-linux-gnu.so
pytrap/helpers.py
pytrap/__init__.py
