Metadata-Version: 2.1
Name: nemea-pytrap
Version: 0.17.0
Summary: Python extension of the NEMEA project.
Home-page: https://github.com/CESNET/Nemea-Framework
Author: Tomas Cejka
Author-email: cejkat@cesnet.cz
Maintainer: Tomas Cejka
Maintainer-email: cejkat@cesnet.cz
License: BSD
Platform: Linux
Classifier: Development Status :: 4 - Beta
Classifier: License :: OSI Approved :: GNU General Public License v3 (GPLv3)
Classifier: Operating System :: POSIX :: Linux
Classifier: Programming Language :: C
Classifier: Programming Language :: Python :: 3
Classifier: Programming Language :: Python :: 3.6
Classifier: Programming Language :: Python :: Implementation :: CPython
Classifier: Topic :: Software Development :: Libraries
Classifier: Topic :: System :: Networking :: Monitoring
